purifier.py
purifier-0.2.16.dist-info/LICENSE
purifier-0.2.16.dist-info/WHEEL
purifier-0.2.16.dist-info/METADATA
purifier-0.2.16.dist-info/RECORD
