Metadata-Version: 2.1
Name: purifier
Version: 0.2.16
Summary: A simple scraping library.
License: AGPL-3.0-or-later
Author: Gleb Akhmerov
Author-email: nontrivial-analysis@proton.me
Requires-Python: >=3.9,<4.0
Classifier: License :: OSI Approved :: GNU Affero General Public License v3 or later (AGPLv3+)
Classifier: Programming Language :: Python :: 3
Classifier: Programming Language :: Python :: 3.10
Classifier: Programming Language :: Python :: 3.9
Requires-Dist: beautifulsoup4 (>=4.11.1,<5.0.0)
Requires-Dist: cloudscraper (>=1.2.60,<2.0.0)
Requires-Dist: jq (>=1.2.2,<2.0.0)
Requires-Dist: jsonfinder (>=0.4.2,<0.5.0)
Requires-Dist: lxml (>=4.9.1,<5.0.0)
Requires-Dist: parsy (>=1.4.0,<2.0.0)
Requires-Dist: requests (>=2.28.1,<3.0.0)
Project-URL: Homepage, https://github.com/gleb-akhmerov/purifier
